djpub/__init__.py
djpub/urls.py
djpub/utils.py
djpub/version.py
djpub/backends/__init__.py
djpub/backends/jinja2.py
djpub/decorators/__init__.py
djpub/decorators/base.py
djpub/mixins/__init__.py
djpub/mixins/base.py
djpub/views/__init__.py
djpub/views/common.py
djpub/views/examples/__init__.py
djpub/views/examples/SomeCoolBlog/__init__.py
djpub/views/examples/SomeCoolBlog/djpub_urls.py
djpub/views/examples/SomeCoolBlog/views.py
djpub-0.0.5.dist-info/METADATA
djpub-0.0.5.dist-info/WHEEL
djpub-0.0.5.dist-info/top_level.txt
djpub-0.0.5.dist-info/RECORD
